Metadata-Version: 2.4
Name: sc-file
Version: 4.2.1
Summary: Utility & Library for decoding stalcraft assets
Author-email: onejeuu <mail@66rk.ru>
License-Expression: MIT
Project-URL: Homepage, https://github.com/onejeuu/sc-file
Project-URL: Repository, https://github.com/onejeuu/sc-file
Project-URL: Documentation, https://sc-file.readthedocs.io
Requires-Python: >=3.11
License-File: LICENSE
Requires-Dist: click<9.0.0,>=8.2.0
Requires-Dist: lz4<5.0.0,>=4.4.0
Requires-Dist: numpy<3.0.0,>=2.3.0
Requires-Dist: rich<15.0.0,>=14.1.0
Requires-Dist: zstandard>=0.25.0
Dynamic: license-file
